sandbox/__init__.py
sandbox/manage.py
sandbox/home/__init__.py
sandbox/home/models.py
sandbox/home/migrations/0001_initial.py
sandbox/home/migrations/0002_create_homepage.py
sandbox/home/migrations/0003_eventregistrationpage.py
sandbox/home/migrations/0004_formfield.py
sandbox/home/migrations/__init__.py
sandbox/sandbox/__init__.py
sandbox/sandbox/urls.py
sandbox/sandbox/wsgi.py
sandbox/sandbox/settings/__init__.py
sandbox/sandbox/settings/base.py
sandbox/sandbox/settings/dev.py
sandbox/sandbox/settings/production.py
sandbox/search/__init__.py
sandbox/search/views.py
wagtailzoom/__init__.py
wagtailzoom/admin.py
wagtailzoom/api.py
wagtailzoom/apps.py
wagtailzoom/errors.py
wagtailzoom/forms.py
wagtailzoom/models.py
wagtailzoom/tests.py
wagtailzoom/views.py
wagtailzoom/wagtail_hooks.py
wagtailzoom/widgets.py
wagtailzoom/migrations/0001_initial.py
wagtailzoom/migrations/0002_remove_zoomsettings_api_key_and_more.py
wagtailzoom/migrations/__init__.py
wagtailzoom/templates/wagtailzoom/zoom_integration_form.html
wagtailzoom/templates/wagtailzoom/widgets/zoom_event_select_widget.html
wagtailzoom/templates/wagtailzoom/widgets/zoom_event_select_widget_js.html
wagtail_zoom_integration-0.0.9.dist-info/METADATA
wagtail_zoom_integration-0.0.9.dist-info/WHEEL
wagtail_zoom_integration-0.0.9.dist-info/top_level.txt
wagtail_zoom_integration-0.0.9.dist-info/RECORD
