Metadata-Version: 2.4
Name: wagtail-zoom-integration
Version: 0.0.9
Summary: Integrate automated Zoom Events registration in Wagtail Form Builder Pages.
Home-page: https://github.com/erick-otenyo/wagtail-zoom-integration
Author: Erick Otenyo
Author-email: otenyo.erick@gmail.com
License: MIT
Classifier: Development Status :: 4 - Beta
Classifier: Environment :: Web Environment
Classifier: Intended Audience :: Developers
Classifier: License :: OSI Approved :: MIT License
Classifier: Operating System :: OS Independent
Classifier: Programming Language :: Python :: 3 :: Only
Classifier: Programming Language :: Python :: 3.9
Classifier: Programming Language :: Python :: Implementation :: CPython
Classifier: Topic :: Software Development :: Libraries :: Application Frameworks
Classifier: Topic :: Software Development :: Libraries :: Python Modules
Requires-Python: >=3.9
Requires-Dist: wagtail>=7.0
Requires-Dist: requests>=2.31.0
Requires-Dist: iso8601>=1.1.0
